pyPIDTuneMethods/ControlSys.py
pyPIDTuneMethods/PIDRecipe.py
pyPIDTuneMethods/PIDTuneMethods.py
pyPIDTuneMethods/PIDTuneMethodsAbout.py
pyPIDTuneMethods/PIDTuneMethods_rc.py
pyPIDTuneMethods/PlotWidget.py
pyPIDTuneMethods/Ui_pid_tune_methods_about_window.py
pyPIDTuneMethods/Ui_pid_tune_methods_main_window.py
pyPIDTuneMethods/Utils.py
pyPIDTuneMethods/__init__.py
pyPIDTuneMethods/control_utils.py
pyPIDTuneMethods/setup.py
pyPIDTuneMethods/ui/Ui_pid_tune_methods_about_window.ui
pyPIDTuneMethods/ui/Ui_pid_tune_methods_main_window.ui
pyPIDTuneMethods/ui/icons/Calculator-32.png
pyPIDTuneMethods/ui/icons/PIDTuneMethods.qrc
pyPIDTuneMethods/ui/icons/barchart-bw-16.png
pyPIDTuneMethods/ui/icons/barchart-col-16.png
pyPIDTuneMethods/ui/icons/cyclic-process-16.png
pyPIDTuneMethods/ui/icons/diagramm-16.png
pyPIDTuneMethods/ui/icons/exit-16.png
pyPIDTuneMethods/ui/icons/help-desk-icon-16.png
pyPIDTuneMethods/ui/icons/info-sign-16.png
pyPIDTuneMethods/ui/icons/line-graph-16.png
pyPIDTuneMethods-0.3.5.dist-info/LICENSE
pyPIDTuneMethods-0.3.5.dist-info/METADATA
pyPIDTuneMethods-0.3.5.dist-info/WHEEL
pyPIDTuneMethods-0.3.5.dist-info/top_level.txt
pyPIDTuneMethods-0.3.5.dist-info/RECORD
