Metadata-Version: 2.1
Name: pyPIDTuneMethods
Version: 0.3.5
Summary: A PID controller design and tuning application
Home-page: https://sourceforge.net/projects/pypidtunemethods/
Author: ElBar
Author-email: eleftherios.barbas@gmail.com
License: UNKNOWN
Platform: UNKNOWN
Classifier: Programming Language :: Python :: 3
Classifier: License :: OSI Approved :: GNU General Public License v3 (GPLv3)
Classifier: Operating System :: OS Independent
